recommenderutils/__init__.py
recommenderutils/models.py
recommenderutils/store.py
recommenderutils-0.1.1.dist-info/LICENSE
recommenderutils-0.1.1.dist-info/METADATA
recommenderutils-0.1.1.dist-info/WHEEL
recommenderutils-0.1.1.dist-info/top_level.txt
recommenderutils-0.1.1.dist-info/RECORD
