Metadata-Version: 2.1
Name: recommenderutils
Version: 0.1.1
Summary: Recommender system for Crisp ML
Home-page: https://gitlab.com/brewedlogic/hq-pos/crisp-ml/-/tree/master/recommender-builder
Author: Ron Medina
Author-email: ron@brewedlogic.com
License: UNKNOWN
Platform: UNKNOWN
Classifier: Programming Language :: Python :: 3
Classifier: Operating System :: OS Independent
Requires-Python: >=3.7
Requires-Dist: scikit-learn (>=0.23.0)
Requires-Dist: numpy (>=1.18.4)
Requires-Dist: pandas (>=1.0.3)
